advancedmaths_UniquePython/__init__.py
advancedmaths_UniquePython/algebra.py
advancedmaths_UniquePython/arithmetic.py
advancedmaths_UniquePython/factors.py
advancedmaths_UniquePython/geometry.py
advancedmaths_UniquePython/statistics.py
advancedmaths_UniquePython-0.0.1.dist-info/LICENSE
advancedmaths_UniquePython-0.0.1.dist-info/METADATA
advancedmaths_UniquePython-0.0.1.dist-info/WHEEL
advancedmaths_UniquePython-0.0.1.dist-info/top_level.txt
advancedmaths_UniquePython-0.0.1.dist-info/RECORD
