Metadata-Version: 2.1
Name: advancedmaths_UniquePython
Version: 0.0.1
Summary: A Python package for advanced mathematical operations
Author-email: Ananyo Bhattacharya <ananyobhattacharya10@gmail.com>
Classifier: Programming Language :: Python :: 3
Classifier: License :: OSI Approved :: MIT License
Classifier: Operating System :: OS Independent
Requires-Python: >=3.8
License-File: LICENSE
